semaphore_win_ctypes/__init__.py
semaphore_win_ctypes/semaphore_win_ctypes.py
semaphore_win_ctypes-0.1.2.dist-info/AUTHORS.rst
semaphore_win_ctypes-0.1.2.dist-info/LICENSE
semaphore_win_ctypes-0.1.2.dist-info/METADATA
semaphore_win_ctypes-0.1.2.dist-info/WHEEL
semaphore_win_ctypes-0.1.2.dist-info/top_level.txt
semaphore_win_ctypes-0.1.2.dist-info/RECORD
