Metadata-Version: 2.1
Name: semaphore_win_ctypes
Version: 0.1.2
Summary: A ctypes wrapper for Windows Semaphore Objects
Home-page: https://github.com/ralexander-phi/semaphore_win_ctypes
Author: Robert Alexander
Author-email: raalexander.phi@gmail.com
License: MIT license
Keywords: semaphore_win_ctypes
Platform: UNKNOWN
Classifier: Development Status :: 4 - Beta
Classifier: Intended Audience :: Developers
Classifier: License :: OSI Approved :: MIT License
Classifier: Natural Language :: English
Classifier: Programming Language :: Python :: 3
Classifier: Programming Language :: Python :: 3.7
Classifier: Programming Language :: Python :: 3.8
Classifier: Programming Language :: Python :: 3.9
Classifier: Programming Language :: Python :: 3.10
Requires-Python: >=3.5
